te5t9527/__init__.py
te5t9527/cli.py
te5t9527/graphviz.py
te5t9527/test.py
te5t9527/version.py
te5t9527/commands/__init__.py
te5t9527/commands/cmd1/__init__.py
te5t9527/fonts/pingfang.ttf
te5t9527-0.0.16.dist-info/METADATA
te5t9527-0.0.16.dist-info/WHEEL
te5t9527-0.0.16.dist-info/entry_points.txt
te5t9527-0.0.16.dist-info/top_level.txt
te5t9527-0.0.16.dist-info/RECORD
