Metadata-Version: 2.1
Name: te5t9527
Version: 0.0.16
Summary: test python publish by travis-ci
Home-page: https://github.com/Secbone/py_publish_test
Author: Secbone
Author-email: secbone@gmail.com
License: MIT
Platform: UNKNOWN
Requires-Python: >=3.5
Requires-Dist: pandas
